vercel_storage/__init__.py
vercel_storage/blob.py
vercel_storage/cli.py
vercel_storage/vercel-blob.code-workspace
vercel_storage/.devcontainer/devcontainer.json
vercel_storage-0.0.1.dist-info/entry_points.txt
vercel_storage-0.0.1.dist-info/LICENSE
vercel_storage-0.0.1.dist-info/WHEEL
vercel_storage-0.0.1.dist-info/METADATA
vercel_storage-0.0.1.dist-info/RECORD
