Metadata-Version: 2.1
Name: vercel_storage
Version: 0.0.1
Summary: A wrapper around the vercel storage blob api
Keywords: vercel,api,storage
Author-email: Noe Nieto <nnieto@noenieto.com>
Requires-Python: ~=3.9
Classifier: License :: OSI Approved :: MIT License
Classifier: Development Status :: 1 - Planning
Classifier: Intended Audience :: Developers
Classifier: Operating System :: OS Independent
Classifier: Programming Language :: Python :: 3
Requires-Dist: requests >=2.6
Requires-Dist: click >= 8.1.7
Requires-Dist: tabulate >= 0.9.0
Requires-Dist: flit ; extra == "packaging"
Requires-Dist: pytest ; extra == "test"
Requires-Dist: pytest-cov ; extra == "test"
Requires-Dist: requests-mock[fixture] ; extra == "test"
Requires-Dist: mypy ; extra == "test"
Project-URL: Source, https://github.com/misaelnieto/vercel-storage
Provides-Extra: packaging
Provides-Extra: test
